[{"PoliticalPartyNep":"नेपाल कम्युनिष्ट पार्टी (एकीकृत मार्क्सवादी-लेनिनवादी)","PostID":8,"SymbolID":2,"PostNameNep":"दलित महिला सदस्य","Win":391,"Lead":460,"Rank":1},{"PoliticalPartyNep":"नेपाली काँग्रेस","PostID":8,"SymbolID":1,"PostNameNep":"दलित महिला सदस्य","Win":333,"Lead":383,"Rank":2},{"PoliticalPartyNep":"नेपाल कम्युनिष्ट पार्टी (माओवादी केन्द्र)","PostID":8,"SymbolID":3,"PostNameNep":"दलित महिला सदस्य","Win":151,"Lead":155,"Rank":3},{"PoliticalPartyNep":"नेपाल मजदुर किसान पार्टी ","PostID":8,"SymbolID":13,"PostNameNep":"दलित महिला सदस्य","Win":7,"Lead":5,"Rank":4},{"PoliticalPartyNep":"नयाँ शक्ति पार्टी, नेपाल","PostID":8,"SymbolID":5,"PostNameNep":"दलित महिला सदस्य","Win":6,"Lead":3,"Rank":5}]